.DS_Store
.gitattributes
.travis.yml
AUTHORS
CONTRIBUTING.md
ChangeLog
LICENSE
README.md
requirements.txt
setup.cfg
setup.py
.github/pull_request_template.md
.github/ISSUE_TEMPLATE/bug_report.md
.github/ISSUE_TEMPLATE/feature_request.md
.idea/QuadCellDetector.iml
.idea/misc.xml
.idea/modules.xml
.idea/vcs.xml
.idea/workspace.xml
.ipynb_checkpoints/TestOfCenteredBeam-checkpoint.ipynb
.vscode/settings.json
MeasuredData/20PassSmoothedFFT.png 10,800×3,600 pixels copy.pdf
MeasuredData/DetectorPositionVoltageData.txt
MeasuredData/.ipynb_checkpoints/DetectorPositionVoltageData-checkpoint.txt
data/sweep-jul-1-2019.pkl
demos/DetectorDemo-v0.9.ipynb
demos/QuadCellDetectorDiscusion.ipynb
demos/TestOfCenteredBeam-checkpoint.ipynb
demos/drawings/Apparatus.jpg
demos/drawings/DetectorGeometry.png
demos/drawings/DetectorGeometryOverview.png
demos/drawings/MainChamber.jpg
demos/drawings/detector.png
demos/drawings/.ipynb_checkpoints/DetectorGeometry-checkpoint.png
demos/drawings/.ipynb_checkpoints/SmallGridSize-checkpoint.png
docs/Makefile
docs/conf.py
docs/detector.rst
docs/index.rst
docs/install.rst
docs/modules.rst
docs/requirements.txt
docs/sample_functions.rst
paper/detector.png
paper/paper.bib
paper/paper.md
quadcelldetector.egg-info/PKG-INFO
quadcelldetector.egg-info/SOURCES.txt
quadcelldetector.egg-info/dependency_links.txt
quadcelldetector.egg-info/not-zip-safe
quadcelldetector.egg-info/pbr.json
quadcelldetector.egg-info/requires.txt
quadcelldetector.egg-info/top_level.txt
quadrantdetector/__init__.py
quadrantdetector/detector.py
quadrantdetector/sample_functions.py
tests/detector_test.py