Metadata-Version: 2.1
Name: quadcelldetector
Version: 0.0.1.dev123
Summary: A library to simulate the electronic output resulting from the passage of a gaussian beam over a quadrant cell photodiode
Home-page: https://github.com/university-of-southern-maine-physics/QuadCellDetector
Author: Paul Nakroshis
License: UNKNOWN
Platform: UNKNOWN
Classifier: Development Status :: 4 - Beta
Classifier: Intended Audience :: Science/Research
Classifier: License :: OSI Approved :: BSD License
Classifier: Operating System :: OS Independent
Classifier: Programming Language :: Python :: 3
